<?xml version="1.0" encoding="utf-8" ?>
<dwsync>
<file name="initialize.php" server="192.168.1.9//var/www/html/" local="133000843980700355" remote="133008588110000000" Dst="0" />
<file name=".htaccess" server="192.168.1.9//var/www/html/" local="132716758080000000" remote="133008587120000000" Dst="0" />
<file name="error.php" server="192.168.1.9//var/www/html/" local="132968472605709453" remote="133008588110000000" Dst="0" />
<file name="index.php" server="192.168.1.9//var/www/html/" local="132993446703705507" remote="133008588110000000" Dst="0" />
<file name="mrss.xml" server="192.168.1.9//var/www/html/" local="132665048480000000" remote="133008588110000000" Dst="0" />
<file name="robots.txt" server="192.168.1.9//var/www/html/" local="132994425542654876" remote="133008588470000000" Dst="0" />
<file name="sitemap.xml" server="192.168.1.9//var/www/html/" local="132848012180000000" remote="133008588470000000" Dst="0" />
<file name="under-maintenance.php" server="192.168.1.9//var/www/html/" local="132938629380000000" remote="133008588470000000" Dst="0" />
<file name=".htaccess" server="192.168.1.5//var/www/html/" local="132716758080000000" remote="132991381650000000" Dst="0" />
<file name="error.php" server="192.168.1.5//var/www/html/" local="132968472605709453" remote="132991382080000000" Dst="0" />
<file name="index.php" server="192.168.1.5//var/www/html/" local="132950356275184358" remote="132991382080000000" Dst="0" />
<file name="initialize.php" server="192.168.1.5//var/www/html/" local="132989094085624853" remote="132991382080000000" Dst="0" />
<file name="mrss.xml" server="192.168.1.5//var/www/html/" local="132665048480000000" remote="132991382080000000" Dst="0" />
<file name="robots.txt" server="192.168.1.5//var/www/html/" local="132860045600000000" remote="132991382170000000" Dst="0" />
<file name="sitemap.xml" server="192.168.1.5//var/www/html/" local="132848012180000000" remote="132991382170000000" Dst="0" />
<file name="under-maintenance.php" server="192.168.1.5//var/www/html/" local="132938629380000000" remote="132991382170000000" Dst="0" />
</dwsync>